tinkerbox/bplustree/__init__.py
tinkerbox/bplustree/btree.py
tinkerbox/bplustree/nodes.py
tinkerbox-0.1.0.dist-info/WHEEL
tinkerbox-0.1.0.dist-info/METADATA
tinkerbox-0.1.0.dist-info/RECORD
