Metadata-Version: 2.1
Name: tinkerbox
Version: 0.1.0
Summary: tidbits to play around with
License: MIT
Author: Subodh Lamichhane
Requires-Python: >=3.9,<4.0
Classifier: License :: OSI Approved :: MIT License
Classifier: Programming Language :: Python :: 3
Classifier: Programming Language :: Python :: 3.10
Classifier: Programming Language :: Python :: 3.9
